fastapi_mvp/__init__.py
fastapi_mvp/metrics/__init__.py
fastapi_mvp/metrics/instrument.py
fastapi_mvp/metrics/settings.py
fastapi_mvp/mvp.py
fastapi_mvp/settings/__init__.py
fastapi_mvp/settings/app_settings.py
fastapi_mvp/settings/env_settings.py
fastapi_mvp/settings/settings.py
fastapi_mvp/storage/__init__.py
fastapi_mvp/storage/mongo_storage/__init__.py
fastapi_mvp/storage/mongo_storage/manager.py
fastapi_mvp/storage/mongo_storage/settings.py
fastapi_mvp/storage/mongo_storage/storage.py
fastapi_mvp/storage/protocols.py
fastapi_mvp/storage/s3_storage/__init__.py
fastapi_mvp/storage/s3_storage/settings.py
fastapi_mvp/storage/s3_storage/storage.py
fastapi_mvp-0.4.0.dist-info/LICENSE
fastapi_mvp-0.4.0.dist-info/METADATA
fastapi_mvp-0.4.0.dist-info/WHEEL
fastapi_mvp-0.4.0.dist-info/RECORD
